CHANGELOG.txt
LICENCE.txt
MANIFEST.in
README.txt
setup.py
abilitysize/__init__.py
abilitysize/__version__.py
abilitysize/_internal_utils.py
abilitysize/adapters.py
abilitysize/api.py
abilitysize/auth.py
abilitysize/certs.py
abilitysize/compat.py
abilitysize/cookies.py
abilitysize/exceptions.py
abilitysize/help.py
abilitysize/hooks.py
abilitysize/models.py
abilitysize/packages.py
abilitysize/sessions.py
abilitysize/status_codes.py
abilitysize/structures.py
abilitysize/utils.py
abilitysize.egg-info/PKG-INFO
abilitysize.egg-info/SOURCES.txt
abilitysize.egg-info/dependency_links.txt
abilitysize.egg-info/top_level.txt